bioemu_benchmarks/BIOEMU_RESULTS.md
bioemu_benchmarks/__init__.py
bioemu_benchmarks/aa_utils.py
bioemu_benchmarks/benchmarks.py
bioemu_benchmarks/evaluator_utils.py
bioemu_benchmarks/logger.py
bioemu_benchmarks/multiconf_evaluator.py
bioemu_benchmarks/paths.py
bioemu_benchmarks/results.py
bioemu_benchmarks/samples.py
bioemu_benchmarks/utils.py
bioemu_benchmarks/assets/folding_free_energies_benchmark_0.1/README.md
bioemu_benchmarks/assets/folding_free_energies_benchmark_0.1/folding_free_energies/system_info.csv
bioemu_benchmarks/assets/folding_free_energies_benchmark_0.1/folding_free_energies/testcases.csv
bioemu_benchmarks/assets/folding_free_energies_benchmark_0.1/folding_free_energies/reference_mutants/1EM7_L7A__T44V.pdb
bioemu_benchmarks/assets/folding_free_energies_benchmark_0.1/folding_free_energies/reference_mutants/1EM7_L7A__V39G.pdb
bioemu_benchmarks/assets/folding_free_energies_benchmark_0.1/folding_free_energies/reference_mutants/1EM7_L7A__Y45R.pdb
bioemu_benchmarks/assets/folding_free_energies_benchmark_0.1/folding_free_energies/reference_mutants/1EM7_V54S__D40G.pdb
bioemu_benchmarks/assets/folding_free_energies_benchmark_0.1/folding_free_energies/reference_mutants/1EM7_V54S__D47W.pdb
bioemu_benchmarks/assets/folding_free_energies_benchmark_0.1/folding_free_energies/reference_mutants/1EM7_V54S__V39A.pdb
bioemu_benchmarks/assets/folding_free_energies_benchmark_0.1/folding_free_energies/reference_mutants/1ENH__L32G_F43N.pdb
bioemu_benchmarks/assets/folding_free_energies_benchmark_0.1/folding_free_energies/reference_mutants/1ENH__Q6C.pdb
bioemu_benchmarks/assets/folding_free_energies_benchmark_0.1/folding_free_energies/reference_mutants/1ENH__S4V.pdb
bioemu_benchmarks/assets/folding_free_energies_benchmark_0.1/folding_free_energies/reference_mutants/1GB4_A27K__D48P.pdb
bioemu_benchmarks/assets/folding_free_energies_benchmark_0.1/folding_free_energies/reference_mutants/1GB4_A27K__Q33P.pdb
bioemu_benchmarks-0.0.1.dist-info/METADATA
bioemu_benchmarks-0.0.1.dist-info/WHEEL
bioemu_benchmarks-0.0.1.dist-info/entry_points.txt
bioemu_benchmarks-0.0.1.dist-info/licenses/LICENSE
bioemu_benchmarks-0.0.1.dist-info/licenses/NOTICE
bioemu_benchmarks-0.0.1.dist-info/RECORD
