Metadata-Version: 2.4
Name: bioemu_benchmarks
Version: 0.0.1
Summary: Accompanying set of benchmarks for BioEmu 1.0 paper.
Project-URL: Homepage, https://github.com/microsoft/bioemu-benchmarks
Project-URL: Issues, https://github.com/microsoft/bioemu-benchmarks/issues
Author: BioEmu authors
License-File: LICENSE
License-File: NOTICE
Classifier: Intended Audience :: Science/Research
Classifier: License :: OSI Approved :: MIT License
Classifier: Programming Language :: Python :: 3
Classifier: Topic :: Scientific/Engineering :: Bio-Informatics
Classifier: Topic :: System :: Benchmark
Requires-Python: >=3.10
Requires-Dist: biopython>=1.5.9
Requires-Dist: fire>=0.5.0
Requires-Dist: h5py>=3.10.0
Requires-Dist: joblib>=1.4.2
Requires-Dist: matplotlib>=3.8.0
Requires-Dist: mdtraj>=1.9.9
Requires-Dist: numpy>=1.26.4
Requires-Dist: pandas>=2.1.4
Requires-Dist: pydantic>=2.1.1
Requires-Dist: requests>=2.32.3
Requires-Dist: scikit-learn>=1.5.2
Requires-Dist: scipy>=1.11.4
Requires-Dist: seaborn>=0.13.2
Requires-Dist: tqdm>=4.66.1
Requires-Dist: urllib3<3.0.0
